run.py
mseep_mcp_tools-0.1.1.dist-info/METADATA
mseep_mcp_tools-0.1.1.dist-info/WHEEL
mseep_mcp_tools-0.1.1.dist-info/top_level.txt
mseep_mcp_tools-0.1.1.dist-info/RECORD
